dotfiles/__init__.py
dotfiles/cli.py
dotfiles/compat.py
dotfiles/core.py
dotfiles/utils.py
dotfiles-0.6.5.dist-info/AUTHORS.rst
dotfiles-0.6.5.dist-info/LICENSE.rst
dotfiles-0.6.5.dist-info/METADATA
dotfiles-0.6.5.dist-info/WHEEL
dotfiles-0.6.5.dist-info/entry_points.txt
dotfiles-0.6.5.dist-info/top_level.txt
dotfiles-0.6.5.dist-info/RECORD
