Metadata-Version: 2.1
Name: dotfiles
Version: 0.6.5
Summary: Easily manage your dotfiles
Home-page: https://github.com/jbernard/dotfiles
Author: Jon Bernard
Author-email: jbernard@jbernard.io
License: ISC
Classifier: Programming Language :: Python
Classifier: Programming Language :: Python :: 3
Classifier: License :: OSI Approved :: ISC License (ISCL)
License-File: LICENSE.rst
License-File: AUTHORS.rst
